mochic7b1937c0/__init__.py
mochic7b1937c0/py.typed
mochic7b1937c0-1.0.1.dist-info/LICENSE
mochic7b1937c0-1.0.1.dist-info/METADATA
mochic7b1937c0-1.0.1.dist-info/WHEEL
mochic7b1937c0-1.0.1.dist-info/top_level.txt
mochic7b1937c0-1.0.1.dist-info/RECORD
