Metadata-Version: 2.1
Name: mochic7b1937c0
Version: 1.0.1
Author-email: Ben Hardcastle <ben.hardcastle@alleninstitue.org>
License: MIT
Project-URL: Repository, https://github.com//mochic7b1937c0
Project-URL: Issues, https://github.com//mochic7b1937c0/issues
Classifier: Development Status :: 3 - Alpha
Classifier: Programming Language :: Python :: 3
Classifier: Programming Language :: Python :: 3.9
Classifier: Programming Language :: Python :: 3.10
Classifier: Programming Language :: Python :: 3.11
Classifier: License :: OSI Approved :: MIT License
Classifier: Operating System :: Microsoft :: Windows
Classifier: Operating System :: POSIX :: Linux
Requires-Python: >=3.9
License-File: LICENSE
